s4gpy/__init__.py
s4gpy/__main__.py
s4gpy/s4gpy.py
s4gpy/s4gsession.py
s4gpy/utils.py
s4gpy/api/__init__.py
s4gpy/api/companyapi.py
s4gpy/api/consoapi.py
s4gpy/api/credentials.py
s4gpy/api/direct.py
s4gpy/api/netflixapi.py
s4gpy/api/user.py
s4gpy/api/utils.py
s4gpy-0.1.0.dist-info/METADATA
s4gpy-0.1.0.dist-info/README.md
s4gpy-0.1.0.dist-info/WHEEL
s4gpy-0.1.0.dist-info/top_level.txt
s4gpy-0.1.0.dist-info/RECORD
