Metadata-Version: 2.1
Name: s4gpy
Version: 0.1.0
Summary: S4G/discoverability API Wrapper.
Home-page: https://github.com/stream-for-good/s4g-client-py
Author: Nicolas Herbaut
Author-email: nicolas.herbaut@univ-paris1.fr
License: Apache 2.0
Keywords: streaming,recommendation,science
Platform: UNKNOWN
Classifier: Development Status :: 4 - Beta
Classifier: Intended Audience :: Developers
Classifier: Natural Language :: English
Classifier: License :: OSI Approved :: Apache Software License
Classifier: Programming Language :: Python
Classifier: Programming Language :: Python :: 3.7
Classifier: Programming Language :: Python :: 3.8
Classifier: Programming Language :: Python :: 3.9
Requires-Python: >= 3.7
License-File: LICENSE.txt
License-File: README.md
Requires-Dist: requests (~=2.25.1)
Requires-Dist: munch (~=2.5.0)
